{
  "task_description": "{'component_name': 'Main Container for NeonColorPicker', 'description': 'Primary container for NeonColorPicker implementation: A simple color picker application that allows users to select and preview neon green and neon blue colors. The app provides a user-friendly interface to choose between these two vibrant neon colors and see the selected color applied to a preview area.', 'framework': 'react', 'platform': 'web', 'container': '{\n  "name": "ColorCraft frontend Container",\n  "features": [\n    {\n      "name": "Neon Green Picker",\n      "description": "Allows users to select neon green color and preview it in a display area.",\n      "isEnabled": true\n    },\n    {\n      "name": "Neon Blue Picker",\n      "description": "Allows users to select neon blue color and preview it in a display area.",\n      "isEnabled": true\n    }\n  ],\n  "techStack": {\n    "frontend": [\n      "React JS"\n    ],\n    "backend": [\n      "None"\n    ],\n    "language": [\n      "JavaScript (ES6+)"\n    ]\n  },\n  "colors": {\n    "primary": "#39FF14",\n    "secondary": "#1F51FF",\n    "accent": "#00FFFF"\n  },\n  "theme": "light",\n  "layoutDescription": "The UI consists of two large color buttons or swatches labeled \'Neon Green\' and \'Neon Blue\'. When a user clicks on a color, a preview area updates to show the selected color. The layout is clean, with the color options at the top and the preview area below."\n}'}",
  "tasks": {},
  "next_task_id": 1
}